fee_lab_to_nwb/__init__.py
fee_lab_to_nwb/general_interfaces/__init__.py
fee_lab_to_nwb/general_interfaces/audiointerface.py
fee_lab_to_nwb/happ_ecephys/__init__.py
fee_lab_to_nwb/happ_ecephys/convert_session.py
fee_lab_to_nwb/happ_ecephys/happecephysnwbconverter.py
fee_lab_to_nwb/happ_ecephys/happmotifinterface.py
fee_lab_to_nwb/happ_ecephys/utils.py
fee_lab_to_nwb/happ_ecephys/widgets/__init__.py
fee_lab_to_nwb/happ_ecephys/widgets/widgets.py
fee_lab_to_nwb/scherrer_ophys/__init__.py
fee_lab_to_nwb/scherrer_ophys/convert_session.py
fee_lab_to_nwb/scherrer_ophys/scherrerophysimagingextractor.py
fee_lab_to_nwb/scherrer_ophys/scherrerophysimaginginterface.py
fee_lab_to_nwb/scherrer_ophys/scherrerophysnwbconverter.py
fee_lab_to_nwb/scherrer_ophys/scherrerophyssegmentationextractor.py
fee_lab_to_nwb/scherrer_ophys/scherrerophyssegmentationinterface.py
fee_lab_to_nwb/scherrer_ophys/utils.py
fee_lab_to_nwb-1.1.0.dist-info/LICENSE
fee_lab_to_nwb-1.1.0.dist-info/METADATA
fee_lab_to_nwb-1.1.0.dist-info/WHEEL
fee_lab_to_nwb-1.1.0.dist-info/top_level.txt
fee_lab_to_nwb-1.1.0.dist-info/RECORD
