Metadata-Version: 2.1
Name: fee-lab-to-nwb
Version: 1.1.0
Summary: NWB conversion scripts, functions, and classes for the Fee lab.
Home-page: https://github.com/catalystneuro/fee-lab-to-nwb
Author: Ben Dichter, Cody Baker, and Szonja Weigl
Author-email: ben.dichter@catalystneuro.com
License: UNKNOWN
Platform: UNKNOWN
Requires-Python: >=3.7
Requires-Dist: nwbinspector
